{
  "branch": "feature/voice",
  "items": [
    {
      "id": "1766383927017",
      "created_at": "2025-12-22T15:12:07.017633754+09:00",
      "text": "완성했다 브로"
    },
    {
      "id": "1766383945785",
      "created_at": "2025-12-22T15:12:25.785356982+09:00",
      "text": "음성 인식 이 지금 렌전더리로 능딸이기 ㄴ한데 이것만 고치면 해결이다"
    },
    {
      "id": "1766383965894",
      "created_at": "2025-12-22T15:12:45.894288365+09:00",
      "text": "그런데데 생각해보니까 지금 log입력창 커서 위치가 이상하다 이거고치고"
    },
    {
      "id": "1766383979542",
      "created_at": "2025-12-22T15:12:59.542079644+09:00",
      "text": "고치기전에 먼저 커밋하자 push도 하고"
    },
    {
      "id": "1766450982783",
      "created_at": "2025-12-23T09:49:42.783434607+09:00",
      "text": "지금 음성인식 성능만 떨어져서 그렇지 남은 기능들은 다 완성했따."
    },
    {
      "id": "1766451071931",
      "created_at": "2025-12-23T09:51:11.931489366+09:00",
      "text": "push 된거는 voice 기능 성능 향상한거다"
    },
    {
      "id": "1766451111634",
      "created_at": "2025-12-23T09:51:51.634773533+09:00",
      "text": "성능향상은 지도도가 보내준거 codex 한테 해달라고 했따"
    },
    {
      "id": "1766451120879",
      "created_at": "2025-12-23T09:52:00.879347952+09:00",
      "text": "------------"
    }
  ]
}